{"tune_id": 13399, "name": "One Summer's Morning", "type": "strathspey", "meter": "4/4", "mode": "Dmajor", "settings": [{"setting_id": 23577, "mode": "Dmajor", "abc": "|:F<d A<B F2 E<D|d2 c<A B>A B<d|F<d A<B F2 E<D|D<F A<F E2 B<A|\nF<d A<B F2 E<D|A<d c<d B<d A<d|F<d A<B F2 E<F|A2 D2 D4:|\nFD DA, A,2 D<F|F<D E<F G>F E<G|FD DA, A,2 D<F|F<E D<F EA, A,2|\nFD DA, A,2 D<F|F<D E<F G>F E<G|A<c d<A B<d A<F|G<F E<G FD D2:|", "username": "Rachael", "date": "2014-02-17 13:42:10", "composer": "Dougie MacLean"}]}