{"tune_id": 15846, "name": "Cairo", "type": "waltz", "meter": "3/4", "mode": "Gmajor", "settings": [{"setting_id": 29814, "mode": "Gmajor", "abc": "M:9/8\n|:DEG|(B3 B2)d BAG|(A3 A)GA BAG|(E3 E2)G E2D|B,6 B,CD|\n(E3 E2)G E2D|(B,3 B,2)G EDB,|(A,3 A,)G,A, B,A,G,|1 G,6:|2 (G,3 G,)G,A, B,CD||\n|:(E3E2)G E2D|(B,3 B,) G,A, B,CD|(E3 E2)D E2G|(B3 B)G,A, (3B,CD|\n(E3 E2)G E2D|(B,3B,2)G EDB,|(A,3 A,)G,A, B,A,G,|1 (G,3 G,)G,A, B,CD:|2 G,6||", "username": "DomW", "date": "2017-02-12 14:36:33", "composer": ""}, {"setting_id": 30615, "mode": "Gmajor", "abc": "|:(3DEG|B3d (3BAG|(A2 (3A)GA (3BAG|E3G (3(E2E2)D|B,4 (3B,CD|\nE3G (3(E2E2)D|B,3G (3EDB,|(A,2 (3A,)G,A, (3B,A,G,|1 G,4:|2 (G,2 (3G,)G,A, (3B,CD||\n|:E3G (3(E2E2)D|(B,2 (3B,) G,A, (3B,CD|E3D (3(E2E2)G|(B2 (3B)G,A, (3B,CD|\nE3G (3(E2E2)D|B,3G (3EDB,|(A,2 A,)G,A, (3B,A,G,|1 (G,2 G,)G,A, (3B,CD:|2 G,4||", "username": "northernmunkeh", "date": "2017-07-03 20:34:16", "composer": ""}]}