{"tune_id": 1642, "name": "Wishing Well, The", "type": "jig", "meter": "6/8", "mode": "Dmajor", "settings": [{"setting_id": 1642, "mode": "Dmajor", "abc": "|:F|DFA d2e|fdB BAF|d2B BAF|B/c/dB BAF|\nDFA d2e|fdB BAF|BAF dBA|fac d2:|\n|:B|Adf ~a3|baf afd|~f2g afd|Bdg bge|\nAdf ~a3|baf afd|b2a afd|Ace d2:|\n|:e|fdd ceA|d2g fdB|c2B ceA|~a3 bag|\n~f2d ecA|d2g fdA|FAD GBD|Aec d2:|", "username": "pchaffee", "date": "2003-05-06 17:18:06", "composer": "Tommy Peoples"}, {"setting_id": 35239, "mode": "Dmajor", "abc": "|:DFA d2e|fdB BAF|B3 BAF|dAF GFE|\nDFA d2e|fdB BAF|BAF dBA|fae [1 dAF:|2 d2||\n|:B|Adf a^ga|baf afd|f2g afd|Bdg bge|\nAdf a^ga|baf afd|b2a afd|Ace d2:|\n|:e|f2d edc|dge fdB|c2B cAA|a^ga ba=g|\nf2d edc|dge fdA|FAD GBD|Adc [1 d2:|2 dAF||", "username": "zoronic", "date": "2019-07-06 22:41:17", "composer": "Tommy Peoples"}]}