{"tune_id": 18555, "name": "Editor's Favourite", "type": "strathspey", "meter": "4/4", "mode": "Amajor", "settings": [{"setting_id": 36207, "mode": "Amajor", "abc": "|:TA2 ((3efg) (a<e) f2|e<c e>f Te>c B<e|TA2 ((3efg) (a<e) f2|1 e<c B>c B<A A>B:|2 e<c B>d c<A A>d||\n|:Tc2 (e>c) A>c e<c|{c}d2 (f>d) f<a Tf>d|c>d e>c A>c e<a|1 f>d e<c B/B/B B>d:|2 f>d e<c B/B/B B>c||", "username": "DonaldK", "date": "2019-10-07 13:20:17", "composer": ""}, {"setting_id": 36220, "mode": "Amajor", "abc": "|:TA2 ((3efg) a<e Tf2|(e<c) e>f Te>c B<e|TA2 ((3efg) a<e Tf2|1 (e<c) B>e c<A A<B:|2 (e<c) B>e c<A A<d||\nTc2 (e<c) A>c e<c|d2 (f<d) ((3fga f)<d|c(c/d/ e)>c A>(c e)>=g|f<d e>c (3B/B/B/B B<d|\nTc2 (e<c) A>c e<c|d2 (f<d) ((3fga f)<d|c>d (e>c) (A>c e)>(a|f)<d e>c B/B/B B<d||", "username": "DonaldK", "date": "2019-10-08 14:17:13", "composer": ""}]}