{"tune_id": 3526, "name": "Stumpie", "type": "strathspey", "meter": "4/4", "mode": "Amajor", "settings": [{"setting_id": 3526, "mode": "Amajor", "abc": "|:c>ea2 a/g/f/e/a2|c>ea2 b<BB>d|c>ea2 a/g/f/e/a2|c>eB>d c<AA2:|\n|:c>ee>c d>ff>d|c>ee>c d<BB>d|c>ee>c d>ff>d|c>eB>d c<AA2:|", "username": "Dr. Dow", "date": "2004-09-12 03:19:10", "composer": ""}, {"setting_id": 16554, "mode": "Gmajor", "abc": "|:dc|B2d2 d2cB|c2e2 e2dc|B2d2 d2cB|c2A2 A2dc|\nB2d2 d2cB|c2e2 e2dc|B2g2 A2dc|B2G2 G2:|\n|:dc|B2d2 g3a|gfed g2dc|B2d2 g2fg|a2A2 A2dc|\nB2d2 g3a|gfed g2dc|B2d2 A2dc|B2G2 G2:|\n|:c2|B2d2 d2ef|gfed g4|B2d2 edcB|c2A2 A2c2|\nB2d2 d2ef|gfed g4|BcdB ABcA|B2G2 G2:|\n|:c2|B2d2 edcB|c2e2 fedc|B2d2 edcB|c2A2 A2c2|\nB2d2 edcB|c2e2 fedc|BcdB ABcA|B2G2 G2:|\n|:Bdg2 afgd|Bdg2 aAAc|Bdg2 aggd|BdAc BGGc:|\n|:BddB ceec|BddB cAAc|BddB ceec|BdAc BGGc:|", "username": "Dr. Dow", "date": "2004-09-12 03:41:06", "composer": ""}, {"setting_id": 16555, "mode": "Amajor", "abc": "|:Bdgb afgd|Bdgb aAAc|Bdgb afge|dBAc BGGc:|\n|:BddB c2ec|BddB cAAc|BddB c2ec|BdAc BGGc:|", "username": "Dr. Dow", "date": "2004-09-12 18:53:56", "composer": ""}, {"setting_id": 16556, "mode": "Gmajor", "abc": "|:B>d g2 g/f/e/d/ g2|B>d g2 a*AA>c|B>d g2 g/f/e/d/ g2|B>dA>c B*G G2:|\n|:B>dd>B c>ee>c|B>dd>B c*AA>c|1 B>dd>B c>ee>c|B>dA>c B*G G2:|\n2 B>dd>B c>ee>f|(3gfe d>c B*G G2||", "username": "ceolachan", "date": "2005-12-10 13:31:36", "composer": ""}, {"setting_id": 42230, "mode": "Gmajor", "abc": "|:D|G>B g2 a<f g>e|G>B g2 a<AA<B|G>B g2 a<f g>e|d>BA>c B<G G:|\nc|B>d d/d/d c<e e/e/e|B<dd>B c>AA>c|B>d d/d/d c<ee<g|d<BA>c B>GG>c|\nB>d d/d/d c<e e/e/e|B<dd>B c>AA>B|G>B g2 a<fg>e|d>BA>d B>G G||", "username": "Mike Mixolydian", "date": "2021-10-28 20:40:16", "composer": ""}]}