{"tune_id": 7268, "name": "Cock Your Pistol Charlie", "type": "slide", "meter": "12/8", "mode": "Edorian", "settings": [{"setting_id": 7268, "mode": "Edorian", "abc": "|:E2e e2f g2f e2c|d2B A2F D2E FED|\nE2e e2f g2f e2c|d2B A2F E3 E2D:|\n|:E2B B2A B2A F2A|d2B A2F D2E FED|\nE2B B2A B2A F2A|Bcd A2F E3 E2D:|", "username": "Dr. Dow", "date": "2007-05-26 20:47:59", "composer": ""}, {"setting_id": 18794, "mode": "Edorian", "abc": "|:E2 e e2 f|g2 f e2 c|d2 B A2 F|D2 E F2 D|\nE2 e e2 f|g2 f e2 c|d2 B A2 F|E3 E3:|\n|:E2 B B2 A|B2 A F2 A|d2 B A2 F|D2 E F2 D|\nE2 B B2 A|B2 A F2 A|Bcd A2 F|E3 E3:|", "username": "ceolachan", "date": "2007-05-27 12:11:07", "composer": ""}]}