{"tune_id": 7383, "name": "One Bottle More", "type": "march", "meter": "4/4", "mode": "Eminor", "settings": [{"setting_id": 7383, "mode": "Eminor", "abc": "|:GE|DB D2 DB D2|DB D2 D4|ED E2 ED E2|EDEF G2 G2|\nB2 B2 dB d2|edef g2 g/f/e|d2 gd BABA|G2 E2 E2:|\n|:zB|dB d2 dB d2|dB d2 ef g2|dB d2 dBdg|gd B2 A3 g|\ngf g2 ed e2|BABA G2 Bc|d2 gd BABA|G2 E2 E2:|", "username": "ceolachan", "date": "2007-06-20 13:14:53", "composer": ""}, {"setting_id": 18893, "mode": "Dmajor", "abc": "|:D2 FA D2 FA|dfed dcBA|dfdf dfed|cABc d2:|\ne2 cA e2 cA|gfed cBAG|FGAB Afed|cABc d2:|", "username": "ceolachan", "date": "2007-06-21 05:46:28", "composer": ""}, {"setting_id": 18894, "mode": "Eminor", "abc": "|:DB D2 DB D2|DB D2 D4|ED E2 ED E2|EDEF G2 G2|\nBA B2 d^c d2|ed e2 g2 fe|d2 gd BABA|G2 E2 E2:|\ndB d2 dB d2|dB d2 ef g2|dB d2 dB d2|gd B2 A4|\n[1 gf g2 ed e2|BABA G2 B^c|d2 gd BABA|G2 E2 E2:|\n[2 gfed ^cd =c2|BABA G2 B^c|d2 gd BABA|G2 E2 E2||", "username": "ceolachan", "date": "2007-06-23 18:08:54", "composer": ""}]}