{"tune_id": 82, "name": "Pride Of Petravore, The", "type": "hornpipe", "meter": "4/4", "mode": "Eminor", "settings": [{"setting_id": 82, "mode": "Eminor", "abc": "|:E3 F G3 A|BcBA G2 E2|D3 E F3 G|ABAG F2 D2|\nE3 F G3 A|BcBA G2 A2|B2Bc BAGF|E2D2 E4:|\n|:e2 e2 e2 e2|dBGA B2Bc|BAFG A2 AB|AGED E2 Bd|\ne2 e2 gfge|dBGA B2 GA|B2Bc BAGF|E2D2 E4:|", "username": "Jeremy", "date": "2001-05-25 03:41:14", "composer": "William Houston Collisson"}, {"setting_id": 12581, "mode": "Eminor", "abc": "|:B,D|E3 F G3 A|B>cBA G2 E2|D2 DE FG/F/ FG|AFDF AB/A/ GF|\nE2 EF G2 GA|B>cBA GFGA|B2Bc BAGF|E2 (3FED E2:|\n|:(3Bcd|e2 e/e/e e2 f>e|dBGA B4|B>AFG A4|A>GEF GFGB|\ne2 ef/e/ e2 ge|dBGA B2 GA|B2Bc BAGF|E2 ED E2:|", "username": "ceolachan", "date": "2005-06-03 17:43:55", "composer": "William Houston Collisson"}, {"setting_id": 24216, "mode": "Eminor", "abc": "B,2|:E3 F G3 A|BcBA GEE2|D3 E F3 G|ABAG FE D2|\nE3 F G3 A|BcBA GEGA|B2Bc BAGF|E2 (3EEE E2B,2:|\n|:e2 e2 e2 e2|dBGA B2Bc|BAFG A2 AB|AGED E2 Bd|\ne^def g3e|dBGA B2 GA|B2Bc BAGF|1 E2(3EEE E2Bd:|2 \"*\"E2E2E2||\nP:*Variant - Leave out 1st part's initial pickup note\nE2B,2C2B,2|", "username": "Lucy Rietmann", "date": "2014-05-31 05:17:16", "composer": "William Houston Collisson"}, {"setting_id": 30084, "mode": "Eminor", "abc": "|:E3F G3A|B>cB>A G<E E2|D3E F3G|A>BA>G F<D D2|\nE3F G3A|B>cB>A G<E E2|B2Bc B>AG>F|E2 E2 E2 E2:|\n|:e2 e2 e2 e2|d>BG>A B2 B2|cF F2 F2 F2|AE E2 E2 E2|\ne2 ef g3f/e/|d>BG>A B2 GF|E>BB>c B>AG>F|E2 E2 E2 E2:|", "username": "JACKB", "date": "2017-03-20 00:31:54", "composer": "William Houston Collisson"}, {"setting_id": 30449, "mode": "Aminor", "abc": "A,3B, C3 D|EFED CA,3|G,3 A, B,3 C|DEDC B,G,3|\nA,3 B, C3 D|EFED CA,2E|EEEE EDCB,|A,4- A,4|\n|:A2 A2 A3 A|GECD E3F|EDB,C D3E|DCA,G, A,4|\nA2 B2 c3A|GECD E2 CD|EEEE EDCB,|A,4- A,4:|", "username": "Yooval", "date": "2017-06-05 10:48:56", "composer": "William Houston Collisson"}, {"setting_id": 33761, "mode": "Eminor", "abc": "B,2|:E3F G3A|B>cBA G2E2|D3E F3G|AFDF AB/A/GF|\nE3F G3A|B>cBA GFGA|B2Bc B>AG>F|1 E2 F/E/D E2B,D:|2 E2 F/E/D E2 B/c/d||\n|:e2 ee/e/ e2f>e|d>BG>A B2Bc|B>AFG A2AB|A>GFD E2 B/c/d|\ne2 ee/e/ e2g>e|d>BG>A B2GA|B2Bc B>AG>F|1 E2 F/E/D E2 B/c/d:|2 E2 F/E/D E2 B,D||", "username": "NfldWhistler", "date": "2018-12-22 06:11:09", "composer": "William Houston Collisson"}, {"setting_id": 33762, "mode": "Eminor", "abc": "B,2|:E3F G3A|B>cBA GFE2|D3E F3G|A>BAG FED2|\nE3F G3A|B>cBA GFGA|B2Bc B>AG>F|1 E2FD E2B,D:|2 E2FD E2B/c/d||\n|:e2e2 e2e2|d>BG>A B2Bc|B>AFG A2AB|A>GFG E2 B/c/d|\ne2ef gfge|d>BG>A B2GA|B2Bc B>AFG|1 E2FD E2 B/c/d:|2 E2FD E2B,D||", "username": "NfldWhistler", "date": "2018-12-22 06:49:18", "composer": "William Houston Collisson"}, {"setting_id": 33763, "mode": "Eminor", "abc": "B,2|:E3F G3A|B>cBA GFE2|D3E F3G|A>BAG F2D2|\nE3F G3A|B>cBA GFGA|B2Bc B>AG>F|1 E2E^D E2B,D:|2 E2E^D E2 B/c/d||\n|:e2e2 e2e2|d>BG>A B2Bc|B>AFG A2AB|A>GE^D E2 B/c/d|\ne2e2 e2g>e|d>BG>A B2GA|B>AB>c BAGF|1 E2E^D E2 B/c/d:|2 E2E^D E2B,D||", "username": "NfldWhistler", "date": "2018-12-22 07:03:48", "composer": "William Houston Collisson"}, {"setting_id": 36676, "mode": "Eminor", "abc": "|:E3F G3A|BcBA GEFE|D3E F3G|ABAG FDED|\nEDEF GFGA|BcBA GEFA|B/B/B/B/B/B/B/B/ BAFG|E2ee e4:|\n|:e2e2 e3e|dBGA B2Bc|BAFE F2AB|AGED E2GB|\ncdef gfge|dBGA ~B2GA|B/B/B/B/B/B/B/B/ BAFG|1 E2e2 e4:|2 E2B,2 C2B,2||", "username": "NfldWhistler", "date": "2019-12-01 19:50:34", "composer": "William Houston Collisson"}, {"setting_id": 36680, "mode": "Eminor", "abc": "|:E3F GFGA|BcBA ~G2E2|D3E FEFG|ABAG ~F2D2|\nE3F GFGA|BcBA ~G2E2|B2Bc BA~F2|1 ~G2E2 E2EF:|2 ~G2E2 E2ee/e/||\n|:e2ef g3e|dBGA B2Bc|BAFE F2AB|AGED EFGA|\nBdef g3e|dBGA B2GA|B2Bc BA~F2|1 ~G2E2 E2ee/e/:|2 ~G2E2 E2EF||", "username": "NfldWhistler", "date": "2019-12-02 03:05:59", "composer": "William Houston Collisson"}, {"setting_id": 36681, "mode": "Eminor", "abc": "|:E2EF G2GA|BcBA G2E2|~D3E ~F3G|ABAG F2D2|\nE2EF G2GA|BcBA G2A2|~B3c BAGF|E2B,2 C2B,2:|\n|:e2e2 e2e2|dBGA B3c|AGFE FGAB|AGED EFGB|\ncdef g3e|dBGA B3A|~B3c BAGF|E2B,2 C2B,2:|", "username": "NfldWhistler", "date": "2019-12-02 04:54:41", "composer": "William Houston Collisson"}, {"setting_id": 40364, "mode": "Eminor", "abc": "|:B,D|E3 F G3 A|BcBA G2 E2|D2 DE F2 FG|AFDF A2 GF|\nE3 F G3 A|BcBA GFGA|BABc BAGF|E2 D2 E2:|\n|:(3Bcd|e2 e2 e2 fe|dBGA B2 Bc|BAFG A2 AB|AGED E2 (3Bcd|\ne2 e2 e2 ge|dBGA B2 GA|BABc BAGF|E2 D2 E2:|", "username": "Madeleine Townley", "date": "2021-01-29 05:12:23", "composer": "William Houston Collisson"}, {"setting_id": 43390, "mode": "Eminor", "abc": "B,|:EB,EF G2 (3FGA|BcBA G<E E2|(3DDD DE FD (3EFG|A>BAG FE (3DEF|\nEB,EF G2 (3FGA|BcBA G<E c2|(3BBB Bc BAGF|1 E2 B,2 C2 B,2:|2 E2 (3EEE E2 z2||\n|:c2 c2 c2 zG|{e}dBGA B3 (B|B)F (3FFF FGAB|AGED (3EFG AB\ncdef g>ggG|{e}dBGA B3 ^A|(3BBB Bc BAGF|1 E2 (3EEE E2 z2:|2 E2 B,2 C2 B,2||", "username": "jmeme", "date": "2022-03-18 02:27:09", "composer": "William Houston Collisson"}, {"setting_id": 44793, "mode": "Eminor", "abc": "B,2|:\"Em\"E3F G3A|\"Em\"B>cBA G2 E2|\"D\"D3E F3G|\"D\"A>BAG F2 D2|\n\"Em\" E3F G3A|\"Em\"B>cBA GFGA|\"Bm7\"B2Bc BAGF|1 \"Em\" E2(3FED E2B,D:|2 \"Em\"E2(3FED E2B/c/d||\n|:\"C\" [c2e2] [c2e2] [c3e3] [ce]|\"Em\"d>BG>A B2Bc|\"Bm7\"B>AFG A2AB|\"D\"A>GFG \"Em\"E2 B/c/d|\n\"C\"[c2e2]ef gfge|\"Bm7\"d>BG>A B2GA|\"Em\"B2Bc \"Bm7\"B>AFG|1 \"Em\"E2(3FED E2 B/c/d:|2 \"Em\"E2(3FED E4||", "username": "Edgar Bolton", "date": "2022-09-11 12:58:35", "composer": "William Houston Collisson"}, {"setting_id": 54471, "mode": "Eminor", "abc": "|: \"Em\"~E3 F ~G3 A|\"Em\"BcBA GEEE |\"D\"~D3 E ~F3 G|\"D\"ABAG FDDD|\n\"Em\"~E3 F ~G3 A|\"Em\"BcBA GEGA|\"Bm\"B2Bc BAGF|\"Em\"E2D2 E4:|\n|:\"C\"~e3fe2 e2|\"G\"dBGA B2Bc|\"D\"BAFG A2 AB|\"Em\"AGEF G4|\n\"C\"~e3f g3e|\"G\"dBGA B2 GF|\"C\"EBBc \"Bm\"BAGF|\"Em\"E2D2 E4 :|", "username": "chansherly212", "date": "2025-07-04 12:33:25", "composer": "William Houston Collisson"}, {"setting_id": 55994, "mode": "Dminor", "abc": "|:\"Dm\"D3 E F3 G|ABAG F2 D2|\"C\"C3 D E3 F|GAGF E2 C2|\n\"Dm\"D3 E F3 G|ABAG F2 G2|\"Am\"A2AB AGFE|\"Dm\"D2C2 D4:|\n|:\"Bb\"d2 d2 d2 d2|\"F\"cAFG A2AB|\"Am\"AGEF G2 GA|\"Dm\"GFDC D2 Ac|\n\"Bb\"d2 d2 fefd|\"F\"cAFG A2 FG|\"Am\"A2AB AGFE|\"Dm\"D2C2 D4:|", "username": "leedavis", "date": "2025-12-06 19:20:41", "composer": "William Houston Collisson"}]}