{"tune_id": 10093, "name": "Miss Stewart Of Grantully", "type": "reel", "meter": "4/4", "mode": "Amixolydian", "settings": [{"setting_id": 10093, "mode": "Amixolydian", "abc": "|:e|AAcA eAcA|GGBG BGBg|AAcA eAcA|Eaef cAA:|\nB|Aa^ga eaca|Bgdg BGGB|Aa^ga eaca|faef cAAB|\nAa^ga eaca|Bgdg BGGB|AAcA dBcA|Eaef cAA||", "username": "bogman", "date": "2009-12-10 07:07:49", "composer": "Neil Gow"}, {"setting_id": 56357, "mode": "Amixolydian", "abc": "|:e|A2 c>A c/d/e c2|B<=G B>c d/c/B/A/ GB|A2 c>A c/d/e c2|A<ae>f c<AA:|\ng|a>ea>e a/g/f/e/ a>e|=g>dg>d B>=GG>^g|a>ea>e a/g/f/e/ a>e|f>ea>e c<AA>g|\na>ea>e a/g/f/e/ a>e|=g>dg>d B>=GG>B|A2 c>A c/d/e c2|A<ae>f c<AA||", "username": "niall_kenny", "date": "2026-01-24 10:44:44", "composer": "Neil Gow"}]}