{"tune_id": 11400, "name": "Miss Grace Hay's", "type": "jig", "meter": "6/8", "mode": "Gmajor", "settings": [{"setting_id": 11400, "mode": "Gmajor", "abc": "|:G2 c B2 c|dBd efg|G2 c B2 c|dBG AFD|E2 C CEG|\nF2 D D2 c|B/c/dB cAF|1 G3 G2 D:|2 G3 G2 A||\nd2 g f2 g|afd e^cA|fga B^cd|efd ^cBA|\nafa geg|fdf e^cA|Bgf ed^c|d2 d d=cB|\nc2 c cac|B2 B BgB|ABA ABc|dBG AFD|\nE2C CEG|F2 D D2 c|B/c/dB cAF|G3 G3||", "username": "niall_kenny", "date": "2011-08-07 02:18:43", "composer": ""}, {"setting_id": 28150, "mode": "Gmajor", "abc": "|:D|GFG DB,D|~G3 D2B|A2B c2B|ABG FED|\n~G3 DB,D|ECD EFG|AcB AGF|~G3 G2:|\n|:A|BGB dBG|~c3 ecA|BGd cAf|gBc ~B2A|\nGFG DB,D|ECD EFG|AcB AGF|~G3 G2:|", "username": "zoronic", "date": "2016-01-30 20:13:51", "composer": ""}]}