{"tune_id": 11975, "name": "Halloween", "type": "reel", "meter": "4/4", "mode": "Dminor", "settings": [{"setting_id": 11975, "mode": "Dminor", "abc": "|:A,2|D2DE FEDC|B,4 G,2B,2|A,2DF AGFD|EFGE CDEC|\nD2DE FEDC|B,4 G,2B,2|A,2DF AGFE|F2D2 D2:|\n|:E2|F2EF G2FE|F2ED E2FE|D2FA C2FA|B,2DF A,2=B,^C|\nD^CDE FED=C|B,4 G,2B,2|A,2A2 AGFE|F2D2 D2:|", "username": "Dr. Tøm", "date": "2012-06-14 14:05:55", "composer": ""}, {"setting_id": 55717, "mode": "Bminor", "abc": "|:F2|B2Bc dcBA|G4 E2G2|F2Bd fedB|cdec ABcA|\nB2Bc dcBA|G4 E2G2|F2Bd fedc|d2B2 B2:|\n|:c2|d2cd e2dc|d2cB c2dc|B2df A2df|G2Bd F2^G^A|\nB^ABc dcB=A|G4 E2G2|F2f2 fedc|d2B2 B2:|", "username": "Andrea Abler", "date": "2025-11-02 22:47:52", "composer": ""}, {"setting_id": 55726, "mode": "Dminor", "abc": "V:1\n|:A,2|\"Dm\"D2DE FEDC|\"Gm\"B,4 G,2B,2|\"Dm\"A,2DF AGFD|\"C\"EFGE CDEC|\nV:2\n|:fe|d2z2z2D2|G2GA BAGE|F4D2F2|E2Gc edcG|\nV:1\n\"Dm\"D2DE FEDC|\"Gm\"B,4 G,2B,2|\"Dm\"A,2DF \"A\"AGFE|\"Dm\"F2D2 D2:|\nV:2\nA4F2A2|G2GA BAGE|F4E2B2|A2df ag:|\nV:1\n|:E2|\"Dm\"F2EF \"A\"G2FE|\"Dm\"F2ED \"A\"E2FE|\"Dm\"D2FA \"F\"C2FA|\"Bb\"B,2DF \"A\"A,2=B,^C|\nV:2\n|:a2|d2z2z2A2|A2GA B2AG|A4 c4|d4 e4|\nV:1\n\"Dm\"D^CDE FED=C|\"Gm\"B,4 G,2B,2|\"Dm\"A,2A2 \"A\"AGFE|\"Dm\"F2D2 D2:|\nV:2\nfed^c d2A2|G2BdF2Bd|D2d4^c2|dBAGF2:|", "username": "Mike Maloney", "date": "2025-11-03 19:46:13", "composer": ""}]}