{"tune_id": 12278, "name": "Rowan Tree, The", "type": "march", "meter": "4/4", "mode": "Gmajor", "settings": [{"setting_id": 12278, "mode": "Gmajor", "abc": "|:G>A|B2 B>A B<dd>g|e>de<g e2 d>G|B2 B>A B<dd>g|e<Bd>B G2-:|\nG>B|d<gg>f f<ee>g|d<Gd>B A2 A>B|d<gg>f f<ee>g|d<Gd>B G2 G>B|\nd<gg>f f<ee>g|d>ed>B B<AA>G|B2 B>A B<dd<g|e<gd>B G2-||", "username": "ceolachan", "date": "2012-11-01 15:01:32", "composer": ""}, {"setting_id": 22949, "mode": "Gmajor", "abc": "V:1\nG/>A/|B2 B>A|B<d d>g|e>d e<g|e>d d>G/A/|\nV:2\nG/>D/|G>F E>F|G<D G>A/B/|c>G c>B|c>B/A/ B/D/E/F/|\nV:1\nB>B B>A|B<d e>d|d<B A>G|G3d:|\nV:2\nG>F E>F|G<D c>A|D2 E>F|G3A:|\nV:1\nd>g g>f|f>e e>g|d>e e/d/c/B/|B2 AG/A/|\nV:2\nB>A B>G|c>B c>G|B>A BG|GF/E/ F/D/E/F/|\nV:1\nB2 B>A|B<d e>d|d>B A2|G3 G/>B/|\nV:2\nG>F E>F|G<D c>A|B>D E>F|G3 G/>F/|\nV:1\nB2 A>G|G3||\nV:2\nG>D c>d|B3||", "username": "JACKB", "date": "2013-11-29 19:37:42", "composer": ""}, {"setting_id": 22950, "mode": "Dmajor", "abc": "V:1\nD/>E/|F2 F>E|F<A A>d|B>A B<d|B>A A>D/E/|\nV:2\nd/>A/|d>c B>c|d<A D>E/F/|G>D G>F|G>F/E/ F/A/B/c/|\nV:1\nF>F F>E|F<A B>A|A<F E>D|D3A:|\nV:2\nd>c B>c|d<A G>E|A2 B>c|d3E:|\nV:1\nA>d d>c|c>B B>d|A>B B/A/G/F/|F2 ED/E/|\nV:2\nF>E F>D|G>F G>D|F>E FD|dc/B/ c/A/B/c/|\nV:1\nF2 F>E|F<A B>A|A>F E2|D3 D/>F/|\nV:2\nd>c B>c|d<A G>E|F>A B>c|d3 d/>c/|\nV:1\nF2 E>D|D3||\nV:2\nd>A G>A|F3||", "username": "JACKB", "date": "2013-11-29 19:49:19", "composer": ""}, {"setting_id": 22965, "mode": "Amajor", "abc": "|:A|c>cc>B c<ee>a|f>ef<a f2 e>A|c>cc>B c<ee<a|e<cB>c A2- A:|\n|:c|e>aa>g g<ff>a|e>fe>c c2 B>A|c>cc>B c<ee<a|e<cB>c A2- A:|", "username": "ceolachan", "date": "2013-11-30 20:09:39", "composer": ""}, {"setting_id": 22966, "mode": "Gmajor", "abc": "|:G|B>BB>A B<dd>g|e>de<g e2 d>G|B>BB>A B<dd<g|d<BA>B G2- G:|\n|:B|d>gg>f f<ee>g|d>ed>B B2 A>G|B>BB>A B<dd<g|d<BA>B G2- G:|", "username": "ceolachan", "date": "2013-11-30 20:10:08", "composer": ""}]}