{"tune_id": 12492, "name": "Abbess, The", "type": "barndance", "meter": "4/4", "mode": "Gmajor", "settings": [{"setting_id": 20879, "mode": "Gmajor", "abc": "DGA|B4 B3 c|d4 G4|e3 e edcB|cBAG d2 GF|\nE2 c2 A3 F|D3 d BAGF|E2 cB AB/A/ GF|G4- GDGA|\nB4 B3 c|d4 GABd|e3 e edcB|cBAG d2 GF|\nE2 c2 A3 F|D3 d BAGF|E2 cB AB/A/ GF|G4- GABc||\nd2 dG g3 d|cBAG d3 c|BAGF EccB|BAAB D2 GF|\nE2 c2 A3 F|D3 d BAGF|E2 cB AB/A/ GF|G4- GABc|\nd2 dG g3 d|cBAe ddef|g2 fg e2 dB|[M:3/2] ABef d3 c BAGF|\n[M:4/4]\nE2 c2 A3 F|D3 d BAGF|E2 cB AB/A/ GF|G2 G2- G||", "username": "ceolachan", "date": "2013-02-10 20:08:20", "composer": "Andy Cutting"}, {"setting_id": 20961, "mode": "Gmajor", "abc": "|:B4 B3 c|d3 G G2 Bd|e2 e2- edcB|cBAG d2 GF|\nE2 c2 A2 AF|D2 d2 BAGF|E2 cB ~A2 GF|1 G4 -GDGA:|2 G4 GABc||\nd4 e3 d|cBAG d2 dc|BAGF EGcB|BAAB D2 GF|\nE2 c2 A3 F|D2 d2 BAGF|E2 cB ~A2 GF|FG G2 GABc|\ndGBd e2 ed|cBce ddef|gBfg e2 dB|[M:3/2] ABef d2 dc BAGF|\n[M:4/4]\nE2 c2 A3 F|D2 d2 BAGF|E2 cB ~A2 GF|FG G2- GDGA||\nB2 BA B2 Bc|d6 Bd|e4 edcB|cBAG d2 GF|\nE2 c2 A3 F|D2 d2 BAGF|E2 cB ~A2 GF|G2 G2 GDGA|\nB2 BA B2 Bc|d8|z e3 edcB|cBAG d2 GF|\nE2 c2 A3 F|D2 d2 BAGF|E2 cB ~A2 GF|G2 G2 GABc||\nd4 e2 ed|cBAG d2 dc|BAGF EGcB|BAAB D2 GF|\nE2 c2 A3 F|D2 d2 BAGF|E2 cB ~A2 GF|FGGF GABc|\ndGBd e2 dB|cBce ddef|gBfg e2 dB|[M:3/2] ABef d2- dc BAGF|\n[M:4/4]\nE2 c2 A3 F|D2 d2 BAGF|E2 cB ~A2 GF|G2 G2 GDGA||\nB4 B3 c|d6 Bd|e2 e2- edcB|cBAG d2 GF|\nE2 c2 A3 F|D2 d2 BAGF|E2 cB ~A2 GF|G2 G2 GDGA|\nzBBA B2 Bc|d6 Bd|e2 e2- edcB|cBAG d2 GF|\nE2 c2 A3 F|D2 d2 BAGF|E2 cB ~A2 GF|G4 GABc||\nd3 B e3 d|cBAG d2 dc|BAGF EGcB|BAAB D2 GF|\nE2 c2 A2 AF|D2 d2 BAGF|E2 cB ~A2 GF|G2 G2 GABc|\ndGBd e2 dB|cBce ddef|gBfg e2 dB|ABef d3 c|\nBAGF E2 c2|A3 F D2 d2|BAGF E2 cB|~A2 GF G2 GF|G8||", "username": "ceolachan", "date": "2013-02-18 05:38:00", "composer": "Andy Cutting"}, {"setting_id": 42299, "mode": "Gmajor", "abc": "DGA|\"G\"B4 \"Am\"B3 c|\"Bm\"d4 G4|\"C\"e3 e edcB|\"Am\"cBAG \"D\"d2 GF|\n\"Am\"E2 c2 \"D\"A3 F|\"Bm\"D3 d \"Em\"BAGF|\"C\"E2 cB \"D\"AB/A/ GF|\"C\" G4- GDGA|\n\"G\"B4 \"Am\"B3 c|\"Bm\"d4 GABd|\"C\"e3 e edcB|\"Am\"cBAG \"D\"d2 GF|\n\"Am\"E2 c2 \"D\"A3 F|\"Bm\"D3 d \"Em\"BAGF|\"C\"E2 cB \"D\"AB/A/ GF|\"C\" G4- GABc||\n\"G\"d2 dG \"C\"e3 d|\"Am\"cBAG \"D\"d3 c|\"G\"BAGF \"C\"EccB|\"Am\"BAAB \"D\"D2 GF|\n\"Am\"E2 c2 \"D\"A3 F|\"Bm\"D3 d \"Em\"BAGF|\"C\"E2 cB \"D\"AB/A/ GF|\"C\" G4- GABc|\n\"G\"d2 dG \"C\"e3 d|\"Am\"cBAe \"D\"ddef|\"G\"g2 fg \"C\"e2 dB|\"Am\"ABef \"D\"d3 c|\n\"G\"BAGF \"C\"E2 c2|[M:3/2] \"D\"A3 F \"Bm\"D3 d \"Em\"BAGF|[M:4/4] \"C\"E2 cB \"D\"AB/A/ GF|\"C\"G8||", "username": "luddite", "date": "2021-11-08 01:04:11", "composer": "Andy Cutting"}]}