{"tune_id": 145, "name": "Handsome Young Maidens, The", "type": "jig", "meter": "6/8", "mode": "Dmajor", "settings": [{"setting_id": 145, "mode": "Dmajor", "abc": "|:dAG FAE|DFA dcd|eAA GAA|EAA edc\ndAG FAE|DFA dcd|eAA GAA|1 edc d3:|2 edc dAG||\n|:F2 A FAF|G2 B BAG|FGA dAF|EBA BAG|\nF2 A FAF|G2 B BAG|AFA dAF|FEc d3:|", "username": "Jdharv", "date": "2001-06-17 05:13:26", "composer": "Charlie Lennon"}, {"setting_id": 190, "mode": "Amajor", "abc": "|:g|aed cdB|Ace aga|bee dee|bee bag|\naed cdB|Ace aga|bge dBG|BAG A2:|\nB|c2 A EAc|dff fed|cde aec|Bff fed|\nc2 A EAc|dff fed|cde aec|dBe A2 B|\nc2 A EAc|dff fed|cde aec|Bff fed|\ncAA eAA|dAA fed|ece fdf|gfg a3||", "username": "Jdharv", "date": "2001-07-11 06:27:34", "composer": "Charlie Lennon"}, {"setting_id": 12841, "mode": "Dmajor", "abc": "|:dAG FAE|DFA dcd|eAA GAA|EAA edc|\ndAG FAE|DFA dcd|eAA GAA|1 edc d3:|2 edc dAG||\nF2 A FAF|G2 B BAG|FGA dAF|EBA BAG|\nF2 A FAF|G2 B BAG|AFA dAF|FEc d3:|", "username": "Jdharv", "date": "2001-07-11 06:32:34", "composer": "Charlie Lennon"}, {"setting_id": 12842, "mode": "Gmajor", "abc": "|:gdc BcA|GBd gfg|add cdd|Add agf|\ngdc BcA|GBd gfg|afd cAD|AGF G2f:|\n|:B2G DGB|cee edc|Bcd gdB|Aee edc|\nB2G DGB|cee edc|Bcd gdB|cAd G2A:|", "username": "JACKB", "date": "2011-02-07 02:56:35", "composer": "Charlie Lennon"}, {"setting_id": 21704, "mode": "Amajor", "abc": "|:g|aed cdB|Ace aga|bee dee|Bee bag|\naed c2 B|Ac/d/e aga|bee dBG|BAG A2:|\n|:B|c2 A EAc|dff fed|cde aec|Bff fed|\n[1 cAE EA/B/c|dff fed|c2 e aec|dBG A2:|\n[2 cAA eAA|dAd fed|eAe fAf|gAg a2||", "username": "ceolachan", "date": "2013-06-15 08:27:50", "composer": "Charlie Lennon"}, {"setting_id": 28360, "mode": "Amajor", "abc": "|:aed cdB|Ace aga|bee dee|bee dee|Bee bag|aed cdB|\nAce aga|bee dee|1 BAG A2g:|2 BAG A2 B||\n|:c3 ABc|dfe f3|efa fec|B2f fed|c2A EAc|\ndfe f3|1 efe fec|BAG A2B:|2 efe fef|gfg bag||", "username": "Naomi", "date": "2016-02-24 09:01:38", "composer": "Charlie Lennon"}, {"setting_id": 29967, "mode": "Amajor", "abc": "|:g|aed cdB|Ace a3|bee dee|Bee bag|\naed cdB|Ace aga|bee dee|BAG A2:|\n|:B|c2 A EAc|d2d fed|c2e aec|B2B fed|\nc2A EAc|d2d fed [1 ece aec|dBG A2:|\n[2 ede fef|gfg a2||", "username": "Robert Chalmers", "date": "2017-03-01 20:20:39", "composer": "Charlie Lennon"}, {"setting_id": 31100, "mode": "Amajor", "abc": "|:g|aed cdB|Ace a3|bee dee|Bee bag|\naed cdB|Ace aga|bee dBe|ABA A2:|\n|:B|c2 A EAc|d2f fed|cde aec|Bff fed|c2A EAc|\nd2f fed|1 cde aec|dBG A2:|2 ece fdf|geg ba||ga6||", "username": "sixholes", "date": "2017-10-04 09:14:55", "composer": "Charlie Lennon"}, {"setting_id": 40238, "mode": "Amajor", "abc": "|:g|aed cdB|Ace aga|bee dee|bee bag|\naed cdB|Ace aga|bee dBG|BAG A2:|\n|:B|c2 A EAc|d2 f fed|ece aec|B2 f fed|\n[1 c2 A EAc|d2 f fed|e2 e cde|fec A2:|\n[2 c2 A EAc|d2 f fed|~e2 e fef|gfg efg||", "username": "Thomas Foschini", "date": "2021-01-17 15:06:39", "composer": "Charlie Lennon"}, {"setting_id": 46405, "mode": "Dmajor", "abc": "|:dAG FAE|DFA dcd|eAA GAA|EAA edc\ndAG FAE|DFA dcd|eAA GAA|1 edc d3:|2 edc dAG||\n|:F2 A FAF|G2 B BAG|FGA dAF|EBA BAG|\nF2 A FAF|G2 B BAG|AFA dAF|FEc d3:|", "username": "b", "date": "2023-03-10 18:08:20", "composer": "Charlie Lennon"}, {"setting_id": 50877, "mode": "Amajor", "abc": "e|:aed c2B|Ace aga|bee dee|ebb bag|\naed c2B|Ace aga|bee dee|bag a2e:|\n|:~c3 ABc|dcd fed|cee aec|Bff fed|\n[1 ~c3 ABc|dcd fed|e^de fe=d|cdB A2B:|\n[2 ~c3 ABc|dcd fed|e^de f^ef|g^^fg bag||", "username": "Sean Perry", "date": "2024-06-26 15:16:35", "composer": "Charlie Lennon"}, {"setting_id": 53187, "mode": "Dmajor", "abc": "|:dAG FGE|DFA dB/c/d|eAA GAA|EAA edc\ndAG FGE|DFA dB/c/d|eAA GAA|1 edc d3:|2 edc dAG||\n|:F2 A FAF|G2 B BAG|FGA dAF|EBB BAG|\nF2 A dAF|G2 B BAG|AFA def|edc d3:|", "username": "JACKB", "date": "2025-02-10 23:37:52", "composer": "Charlie Lennon"}, {"setting_id": 54199, "mode": "Amajor", "abc": "|:aed cdB|Ace a3|bee dee|Bee bag|\naed cdB|Ace aga|bee dBG|1 BAG A2g:|2 BAG A2B||\n|:c2A EAc|d2f fed|cde aec|B2f fed|\n[1 c2A EAc|d2f fed|cde aec|dBG A2B:|\n[2 c2A EAc|d2f fed|ede fef|gfg bag||", "username": "NielsJohnson", "date": "2025-06-01 15:15:14", "composer": "Charlie Lennon"}, {"setting_id": 55887, "mode": "Amajor", "abc": "e|:aed cdB|Ace aga|bee dee|Bee bag|\naed cdB|Ace aga|bee dee|cdB A3:|\n|:c2 A EAc|d2 f2 ed|ece aec|BBB fed|c2 A EAc|\nd2 f2 ed|1 ece aec|BcB A3:|2 ece fef|gfg bag||", "username": "Six Fingers", "date": "2025-11-23 17:37:52", "composer": "Charlie Lennon"}]}