{"tune_id": 1539, "name": "Castleblaney Piper, The", "type": "jig", "meter": "6/8", "mode": "Dmajor", "settings": [{"setting_id": 1539, "mode": "Dmajor", "abc": "|:FDF ABc|dAG FED|~G3 FGA|BGE AGE|\n~F3 ABc|dAG FED|dfa gec|dAF D3:|\n|:afd fec|dAG FED|~G3 FGA|BGE E2b|\nafd fec|dAG FED|dfa gec|dAF D3:|", "username": "gian marco", "date": "2003-03-21 22:47:37", "composer": "Ed Reavy"}, {"setting_id": 14940, "mode": "Dmajor", "abc": "|:FEF ABc|dAG FED|GBG FGA|BEE E2A|\nFEF ABc|dAG FED|afd gec|dAF D3:|\nafd gec|dAG FED|GBG FGA|BEE E2^g|\nafd gec|dAG FED|afd gec|dAF D3|\nafd gec|dAG FED|GBG FGA|BEE E2^g|\naba gec|dAG FED|faf gec|dAF D3||", "username": "Dr. Dow", "date": "2008-04-13 12:21:20", "composer": "Ed Reavy"}, {"setting_id": 22372, "mode": "Dmajor", "abc": "|:FDF ABc|dfd AGF|GBG EFG|~F3 GFE|\nFDF AFA|ded cde|~f3 gec|1 edc dAG:|2 edc d2e||\nfed gfe|fdB AGF|~G3 FGA|BGE E2e|\nf2a gfe|fed cde|~f3 gec|edc d2e|\nfed gfe|fdB AGF|GBG EFG|~F3 GFE|\n~F3 ~A3|~d3 cde|faf gec|edc dAG||", "username": "slainte", "date": "2013-09-25 11:47:23", "composer": "Ed Reavy"}, {"setting_id": 38047, "mode": "Dmajor", "abc": "|:AG|FDF ABc|dfd AGF|GBG EFG|FDF GFE|\nFDF ABc|dfd cde|faf ged|edc d3:|\ne|fed gfe|fed cAF|GBG FGA|BGE E3|\nf2d g2e|fed cde|faf gec|edc d2e|\nfed gfe|fed cAF|GBG FGA|BGE EFG|\nFDF ABc|dfd cde|faf gec|edc d3||", "username": "fionán", "date": "2020-06-03 17:59:57", "composer": "Ed Reavy"}]}