{"tune_id": 15675, "name": "Bluestack, The", "type": "mazurka", "meter": "3/4", "mode": "Dmajor", "settings": [{"setting_id": 29419, "mode": "Dmajor", "abc": "|:FG|A2 d2 cd|e2 d2 cd|B2 c2 BA|F2 AG FG|\nA2 dB cd|e2 d2 cd|B2 c2 BA|d2 d2:|\nfe|d2 Bd AF|E2 E2 cB|A2 FD ED|B2 A2 FG|\nA2 dB cd|e2 d2 cd|B2 c2 BA|d2 d2:|", "username": "Aurélien Corneille", "date": "2016-12-03 09:47:56", "composer": ""}, {"setting_id": 48098, "mode": "Dmajor", "abc": "|:FG A2 d2|cd e2 d2|cd B2 c2|BA F2 A2|\nFG A2 d2|cd e2 d2|cd B2 c2|BA d2 d2:|\n|:fe d2 B2|AF E2 B2|cB A2 F2|ED B2 A2|\nFG A2 d2|cd e2 d2|cd B2 c2|BA d2 d2:|", "username": "Liam Slivka", "date": "2023-09-05 00:31:52", "composer": ""}]}