{"tune_id": 16443, "name": "Terry Teahan's", "type": "polka", "meter": "2/4", "mode": "Cmajor", "settings": [{"setting_id": 31155, "mode": "Cmajor", "abc": "|:dc {d}cA|GA/B/ cd|eg {a}gf|df/d/ cA|\nGc {d}cA|GA/B/ cd|eg {a}gf|df/d/ cc:|\neg gg|^f/g/a ge|cd/=f/ gd|ed cA|\nGg gg|^f/g/a ge|cd/=f/ gd|ed cc|\neg gg|^f/g/a ge|cd/=f/ gd|ed cA|\nGc {d}cA|GA/B/ cd|eg {a}gf|df/d/ cc||", "username": "Aurélien Corneille", "date": "2017-10-15 17:30:52", "composer": ""}, {"setting_id": 34610, "mode": "Gmajor", "abc": "|:A|GA/G/ ED|E/F/G AB|de/d/ cA|AG ED|\nGA/G/ ED|E/F/G AB|de/d/ cA|AG G:|\nB|d2 dB/d/|ed BG|A2 AB|AG ED|\nd2 dB/d/|ed BG|A/B/c AB|AG GB|\nd2 dB/d/|ed BG|A/B/c AB|AG ED|\nGA/G/ ED|E/F/G AB|de/d/ cA|AG G2||", "username": "Nico", "date": "2019-04-04 21:03:32", "composer": ""}, {"setting_id": 42814, "mode": "Dmajor", "abc": "|:de/d/ BA|B/c/d ef|ab/a/ ge|ed BA|\nde/d/ BA|B/c/d ef|ab/a/ ge|1 ed de:|2 ed df||\na2 a^g/a/|ba fd|e/g/a ef|ed BA|\na2 a^g/a/|ba fd|e/g/a ef|ed df|\na2 a^g/a/|ba fd|e/g/a ef|ed BA|\nde/d/ BA|B/c/d ef|ab/a/ ge|ed de||", "username": "Bregolas", "date": "2022-01-18 19:08:54", "composer": ""}]}