{"tune_id": 16593, "name": "Corriechoillie's Welcome To The Northern Meeting", "type": "march", "meter": "4/4", "mode": "Dmajor", "settings": [{"setting_id": 31537, "mode": "Dmajor", "abc": "|:e|A>B Ad|e>d BA|d>e fa|fe ef|\nA>B Ad|e>d BA|d>e fa|fd d:|\ng|a>f df|e>d BA|d>e fa|fe eg|\na>f df|e>d BA|d>e fa|fd dg|\na>f df|e>d BA|d>e fa|fe ef|\nA>B Ad|e>d BA|d>e fa|fd d||", "username": "Nigel Gatherer", "date": "2017-12-21 10:11:13", "composer": ""}, {"setting_id": 40861, "mode": "Dmajor", "abc": "|:d|A>B Ad|e>d BA|d>e fa|fe ef|\nA>B Ad|e>d BA|d>e fa|fd d:|\ng|a>f df|e>d BA|d>e fa|fe ef|\na>f df|e>d BA|d>e fa|fd dg|\na>f df|e>d BA|d>e fa|fe ef|\nA>B Ad|e>d BA|d>e fa|fd d||", "username": "Theo Redepenning", "date": "2021-03-23 08:31:25", "composer": ""}]}