{"tune_id": 17657, "name": "Glory In The Meeting House", "type": "barndance", "meter": "4/4", "mode": "Dmixolydian", "settings": [{"setting_id": 34054, "mode": "Dmixolydian", "abc": "|:D2d2 dcAG|Acd2 dcAF|D2d2 dcAF|GAGF- FGEF|\nD2d2 dcAG|Acd2 d2de|=fedc A2G^F|GAGF DECD:|\n|:DEFG AcAG|FAGF DECD|DEFG AcAG|F2D2 G4|\nDEFG AcAG|FAGF DECD|DEFG AcAG|F2D2 D4:|", "username": "pbsinclair42", "date": "2019-01-14 22:44:28", "composer": ""}, {"setting_id": 49324, "mode": "Dmixolydian", "abc": "|:D2 d2- dcAG|Ac d2 dcAF|D2 d2- dcAF|GAGF DECD|\nD2 d2- dcAG|Acd2 d3 e|=fedc A3 ^F|GAGF DECD:|\n|:DEFG AcAG|FAGF DECD|DEFG AcAG|F A3 A4|\nDEFG AcAG|FAGF DECD|DEFG AcAG|1 F A3 A4:|2 F D3 D4||", "username": "Aberfoyle Whistler", "date": "2024-01-15 10:38:44", "composer": ""}]}