{"tune_id": 2655, "name": "Spindle Shank, The", "type": "reel", "meter": "4/4", "mode": "Gmajor", "settings": [{"setting_id": 2655, "mode": "Gmajor", "abc": "|:d2ge dBAG|FDAD BDAD|~G3E DGBG|FAdc BGGd:|\n|:gedB cAAg|fdad bdad|gedB cAAc|dega bggf:|", "username": "turophile", "date": "2004-03-14 09:04:49", "composer": ""}, {"setting_id": 15902, "mode": "Gmajor", "abc": "d2 eB dBAG|F/E/D AD BDAF|G2 FE D~G3|FGAc BGGB|\ndgeB dBAG|F/E/D AD BDAF|G2 FE D~G3|FGAc BGBd||\ngedB cBAg|fdad bdaf|gedB cBAB|dega bggf|\ngedB cBAg|fdad bdaf|gedB cBAB|dega b~g3||", "username": "Will Harmon", "date": "2008-09-10 21:53:50", "composer": ""}, {"setting_id": 25569, "mode": "Gmajor", "abc": "|:d2 ge dBAG|F/E/D Ac BGAF|GAGE DEGE|1 FAdc BGGe:|2 FAdc BGGf||\ngedB cAAg|f/e/d ad bdaf|gedB cAA^c|1 dega bggf:|2 dega bgge||", "username": "Phantom Button", "date": "2015-01-06 05:22:06", "composer": ""}]}