{"tune_id": 3382, "name": "Johnny Boyle's", "type": "jig", "meter": "6/8", "mode": "Gmajor", "settings": [{"setting_id": 3382, "mode": "Gmajor", "abc": "|:g2 f efg|d2 B BAB|c2 A AGA|BAB GBd|\ng2 f efg|d2 B BAB|A2 a agf|1 g3 def:|2 g2 f g2 a||\nb2 g gfg|b2 g gfg|a2 f fef|a2 f dfa|\nb2 g gfg|b2 g gfg|eaa agf|1 g2 f g2 a:|2 g3 def||", "username": "Kenny", "date": "2004-08-10 15:57:27", "composer": ""}, {"setting_id": 16441, "mode": "Gmajor", "abc": "|:g2 f efg|d2 B BAB|c2 A AGA|B2 G G2 f|\ng2 f efg|d2 B BAB|c2 a agf|g3:|\nb2 g gfg|b2 g gfg|a2 f fef|a2 f d2 a|\nb2 g gfg|b2 g gfg|e2 a agf|g3:|", "username": "ceolachan", "date": "2008-04-07 14:49:58", "composer": ""}, {"setting_id": 27030, "mode": "Gmajor", "abc": "|:g2 f efg|d2 B BAB|c2 A AGA|B2 G G2 f|\ng2 f efg|d2 B B2 c|A2 a def|1 g2 d e2 f:|2 g3 g2 a||\nb2 g gfg|b2 g gfg|a2 f fef|a2 f d2 g|\nb2 g gfg|b2 g g2 a|e2 a def|1 g3 g2 a:|2 g2 d e2 f||", "username": "Ediot", "date": "2015-08-10 20:59:24", "composer": ""}, {"setting_id": 29195, "mode": "Gmajor", "abc": "|:g2 f efg d2 B BAB|c2 A AGA B2 G GBd|\ng2 f efg d2 B BcB|1 A2 a agf g2 g def:|2 A2 a agf g2 g g2 a:|\n|:b2 g gfg b2 g gfg|a2 f fef a2 f d2 g|\nb2 g gfg b2 g gfg|1 eag fef g2 g g2 a:|2 eag fef g2 g g3:|", "username": "bpundyke", "date": "2016-10-05 15:33:10", "composer": ""}, {"setting_id": 29196, "mode": "Dmajor", "abc": "|:d2 c Bcd A2 F FEF|G2 E E3 F2 D DFA|\nd2 c Bcd A2 F FEF|1 E2 e edc d2 d ABc:|2 E2 e edc d2 d d2 e:|\n|:f2 d dcd f2 d dcd|e2 c cBc e2 c A2 d|\nf2 d dcd f2 d dcd|1 Bed cBc d2 d d2 e:|2 Bed cBc d2 d d3:|", "username": "JACKB", "date": "2016-10-06 13:27:48", "composer": ""}, {"setting_id": 54850, "mode": "Gmajor", "abc": "|:\"C\"g2f efg \"G\"d2B BAB|\"D\"c2B AGA \"G\"B2G GBd|\n\"C\"g2f efg \"G\"d2B BAB|1 \"D\"Ace agf \"G\"g3 def:|2 \"D\"Ace agf \"G\"g3g2a||\n|:\"G\"b2g gfg b2g gfg|\"D/F#\"a2f fef a2fd2g|\n\"Em\"b2g gfg b2g gfg|1 \"D\"Ace \"D/F#\"agf \"G\"g3g2a:|2 \"D\"Ace \"D/F#\"agf \"G\"g3g3||", "username": "Diarmait", "date": "2025-08-15 03:43:15", "composer": ""}]}