{"tune_id": 3676, "name": "New York, The", "type": "jig", "meter": "6/8", "mode": "Cmajor", "settings": [{"setting_id": 3676, "mode": "Cmajor", "abc": "|:a|{a}gec ceg|fd_B Bdf|{a}gec cde|fef {fg}a2 f|\ngec ceg|fd_B def|ece dBG|c3 Tc2 :|\n|:G,|CEG cGE|{G}FEF DED|CEG cGc|ece d2 B|\nced cGE|{G}FEF DEF|ECE FDB,|DCC C2:|", "username": "Erik-Fiddler", "date": "2004-10-10 21:59:40", "composer": "Alex Joe MacEachern"}, {"setting_id": 45717, "mode": "Cmajor", "abc": "|:gec ceg|fd_B _Bdf|gec cde|fef f a2|\ngec ceg|fd_B _Bdf|ece dBG|c3 c3:|\n|:CEG cGE|FEF DED|CEG cGc|ece d2 B|\nced cGE|FEF DEF|ECE FDB,|DCC C3:|", "username": "victor gomez", "date": "2022-12-25 21:28:47", "composer": "Alex Joe MacEachern"}]}