{"tune_id": 4191, "name": "Humours Of Ballingarry, The", "type": "jig", "meter": "6/8", "mode": "Gmajor", "settings": [{"setting_id": 4191, "mode": "Gmajor", "abc": "|:A|BGG dGG|cAG FGA|BAG BdB|cAF G2A|\nBGG dGG|cAG FGA|def gdB|cAF G2:|\n|:B|def gfg|edc BAG|A2a aga|bge edB|\ndef gfg|edc BAB|GBd gdB|cAF G2:|", "username": "slainte", "date": "2005-02-02 06:33:39", "composer": ""}, {"setting_id": 16950, "mode": "Gmajor", "abc": "G2A|BAG dBG|cAG FGA|BAG dBG|cAF G2A|\nBGB BAG|ABc AGA|~B3 cBF|AGG G2 A|\nBAG dAG|cAG FGA|BAG DGB|cAF G2A|\nBGB BAG|ABc AGA|B/c/dB cAF|DGG G2B/d/|\ng3 ~d3|cAG FGA|DGB DGB|cAF GBd|\ng3 ~d3|cAG FGA|~d3 fed|cAF G2d|\ng3 ~d3|cAG FGA|DGB DGB|cAG GBd|\ng3 ~d3|cAG FGA|~d3 fed|cAF G2A||", "username": "Dakotabanjo", "date": "2009-04-07 15:03:42", "composer": ""}, {"setting_id": 16951, "mode": "Gmajor", "abc": "|:A|BGG dGG|cAG FGA|BGG dGG|cAF G2A|\nBGG dGG|cAG FGA|def gdB|cAF G2:|\n|:B|def gfg|edc BAG|A2a aga|bge e2d|\ndef gfg|edc BCA|GBd gdB|cAF G2:|", "username": "Loughcurra", "date": "2010-07-29 09:26:21", "composer": ""}, {"setting_id": 36080, "mode": "Gmajor", "abc": "|:BGG dGG|cAG FGA|BAG B/c/dB|cAF G2A|\nBGG dGG|cAG FGA|def gdB|1 cAF G2A:|2 cAF G2B||\n|:def ~g3|edc BAG|A2a aga|bge edB|\ndef ~g3|edc BAB|GBd gdB|1 cAF GBc:|2 cAF G2A||", "username": "NfldWhistler", "date": "2019-09-27 15:53:27", "composer": ""}, {"setting_id": 45757, "mode": "Gmajor", "abc": "|:A|BGG dGG|cAG FGA|BGG dGB|cAF G2 A|\nBGG dGG|cAG FGA|d^cd fed|cAF G2:|\n|:B|def ~g3|edc BcG|A2~a aga|bge e2B|\ndef ~g3|edc BcA|GBd gdB|cAF G2:|", "username": "James Dumbelton", "date": "2022-12-30 14:08:45", "composer": ""}, {"setting_id": 51147, "mode": "Gmajor", "abc": "BGG dGG|cAG FGA|DBD Bdd|cAF DGd|\nBGG DGG|cAE FGA|[Dd]ef gdB|cAF G,G/G/G|\nGGG, Bdd|[cE]cE Ecc|[BD]BB Bdd|cAF DGd|\nBGG DGG|cAD FGA|def gdB|cAF GA/B/c||\ndef gag|edc DBB|eda aga|bge eBB|\ndef gag|edc DBB|GBd gdB|cAF GBc|\ndef [cg]gg|edc ABG|B/B/AA Aga|abb eBc|\ndef gag|edc [DA]BB|GBd gdB|c3 H[B3G3]||", "username": "benhockenberry", "date": "2024-07-24 23:03:14", "composer": ""}, {"setting_id": 53963, "mode": "Gmajor", "abc": "|:BGG dGG|cAG FGA|BAG BdB|cAF G2A|\nBGG dGG|cAG FGA|def gdB|1 cAF G2A:|2 cAF G2B||\ndef g g/g/g|edc BAG|A2a aga|bge edB|\ndef g g/g/g |edc BAB|GBd gdB|cAF G2|\nB|def g g/g/g|edc BAG|e2a abc'|bag edB|\ndef g g/g/g |edc BAB|GBd gdB|cAF G2||", "username": "Balázs", "date": "2025-04-30 05:45:25", "composer": ""}]}