{"tune_id": 7498, "name": "Teelin Petronella, The", "type": "barndance", "meter": "4/4", "mode": "Gmajor", "settings": [{"setting_id": 7498, "mode": "Gmajor", "abc": "G,A,|:B,2 D2 A,2 D2|G,2 A,B, G,2 B,D|G/A/G FG A2 GA|B2 G2 D2 C2|\nB,2 D2 A,2 D2|G,2 A,B, G,2 B,D|G/A/G FG A2 GA|1 B2 G2 GEDC:|2 B2 G2 GD||\n|:B,C|D2 B2 D2 B2|D2 B2 BAGF|E2 c2 E2 FG|AGFE DCB,C|\nD2 B2 D2 B2|D2 B2 BAGF|E2 c2 E2 FG|AGFA G2:|", "username": "ceolachan", "date": "2007-07-16 16:42:26", "composer": ""}, {"setting_id": 18972, "mode": "Gmajor", "abc": "Ac|:B2 d2 A2 d2|G2 AB G2 Bd|g/a/g fg a2 ga|b2 g2 d2 c2|\nB2 d2 A2 d2|G2 AB G2 Bd|g/a/g fg a2 ga|1 b2 g2 gedc:|2 b2 g2 g2||\n|:Bc|d2 b2 d2 b2|d2 b2 bagf|e2 c'2 e2 fg|agfe dcBc|\nd2 b2 d2 b2|d2 b2 bagf|e2 c'2 e2 fg|agfa g2:|", "username": "ceolachan", "date": "2007-07-18 04:48:26", "composer": ""}, {"setting_id": 22826, "mode": "Dmajor", "abc": "D>E|:F2 A2 E2 A2|D2 E>F D2 F>A|(3ded c>d e2 d>e|f2 d2 A2 G2|\nF2 A2 E2 A2|D2 E>F D2 F>A|(3ded c>d e2 d>e|1 f2 d2 d>BA>G:|2 f2 d2 d>A||\n|:F>G|A2 f2 A2 f2|A2 f2 f>ed>c|B2 g2 B2 c>d|e>dc>B A>GF>G|\nA2 f2 A2 f2|A2 f2 f>ed>c|B2 g2 B2 c>d|e>dc>e d2:|", "username": "ceolachan", "date": "2013-11-22 15:48:18", "composer": ""}]}