{"tune_id": 8100, "name": "Old Station House, The", "type": "reel", "meter": "4/4", "mode": "Adorian", "settings": [{"setting_id": 8100, "mode": "Adorian", "abc": "a3b aged|eggf gedg|edce dcBc|AG=FG E2GA|\ncG~G2 cdeg|dB~B2 d2 (3efg|aged edce|dcBc A2za||\n^gaag aged|eggf gedg|edce dcBc|AG=FG E2GA|\ncG~G2 cdeg|dB~B2 d2 (3efg|aged edce|dcBc A2z^G||\nAeed edcB|Aeed edBG|~E3F ~G3z|Bcd^d edcB|\nAeae edcB|aeAe ed (3Bcd|e2ge aged|ceBe a2z2||\naee=f edcB|Aee=f edBG|~E3F ~G3z|BcdB edcB|\nAeae edcB|aeAe ed (3Bcd|e2ge aged|ceBe A2z2|", "username": "gian marco", "date": "2008-01-01 08:46:58", "composer": "Patrick Ourceau"}]}