{"tune_id": 9408, "name": "Johnny's", "type": "reel", "meter": "4/4", "mode": "Edorian", "settings": [{"setting_id": 9408, "mode": "Edorian", "abc": "|:B2cA BE~E2|BABc dfec|dBAF ~D3E|FDFA dfed|\nB2cA BE~E2|BABc d2Ad|fedf edef|1 dBAF EFGA:|2 dBAF E3z||\n|:B2ed Be~e2|BABc dfec|dBAF ~D3E|FDFA dfed|\nB2ed Be~e2|BABc d2Ad|fedf edef|1 dBAF E3z:|2 dBAF EFGA||", "username": "slainte", "date": "2009-03-05 03:28:46", "composer": ""}, {"setting_id": 20005, "mode": "Ddorian", "abc": "|:A2BG AD~D2|AGAB cedB|cAGE ~C3D|ECEG cedc|\nA2BG AD~D2|AGAB c2Gc|edce dcde|1 cAGE DEFG:|2 cAGE D3z||\n|:A2dc Ad~d2|AGAB cedB|cAGE ~C3D|ECEG cedc|\nA2dc Ad~d2|AGAB c2Gc|edce dcde|1 cAGE D3z:|2 cAGE DEFG||\nK: Ador\n|:e2fd eA~A2|edef gbaf|gedB ~G3A|BGBd gbag|\ne2fd eA~A2|edef g2dg|bagb agab|1 gedB ABcd:|2 gedB A3z||\n|:e2ag ea~a2|edef gbaf|gedB ~G3A|BGBd gbag|\ne2ag ea~a2|edef g2dg|bagb agab|1 gedB A3z:|2 gedB ABcd||", "username": "slainte", "date": "2009-03-05 04:00:25", "composer": ""}, {"setting_id": 24904, "mode": "Edorian", "abc": "dc|:B2 Ad BEEE|BABc dedB|A^GAB ADDE|(3FED FA d2 cd|\nBB Ad BEEE|BABc dcde|fdde dcBA|(3Bcd AF EFGA:|\n|:Beed efed|BABc dedB|A^GAB ADDE|(3FED FA d2 cd|\nBeed efed|BABc dcde|fdde dcBA|(3Bcd AF EFGA:|", "username": "GaryAMartin", "date": "2014-10-03 13:22:07", "composer": ""}]}